pyward/__init__.py
pyward-3.0.data/scripts/__init__.py
pyward-3.0.dist-info/METADATA
pyward-3.0.dist-info/WHEEL
pyward-3.0.dist-info/top_level.txt
pyward-3.0.dist-info/RECORD
