Metadata-Version: 2.1
Name: pyward
Version: 3.0
Summary: Stabilizes Code and Makes It Secure
Home-page: https://github.com/pyward/pyward
Author: Rachel Anthony
Author-email: dev@pyward.com
Classifier: Development Status :: 3 - Alpha
Classifier: Intended Audience :: Developers
Classifier: License :: OSI Approved :: MIT License
Classifier: Programming Language :: Python :: 3
Classifier: Programming Language :: Python :: 3.6
Classifier: Programming Language :: Python :: 3.7
Classifier: Programming Language :: Python :: 3.8
Classifier: Programming Language :: Python :: 3.9
Requires-Dist: requests
